ssf/__init__.py
ssf/run.py
simple_selfstudy_fish-0.3.0.dist-info/METADATA
simple_selfstudy_fish-0.3.0.dist-info/WHEEL
simple_selfstudy_fish-0.3.0.dist-info/top_level.txt
simple_selfstudy_fish-0.3.0.dist-info/RECORD
