Metadata-Version: 2.1
Name: simple_selfstudy_fish
Version: 0.3.0
Summary: simple fish selfstudy model
Author-email: elnath1002 <elnath1002@naver.com>
License: MIT
Project-URL: homepage, https://github.com/WhiteCapella/simple_selfstudy_fish
Project-URL: issue, https://github.com/WhiteCapella/simple_selfstudy_fish/issues
Requires-Python: ==3.11.*
Requires-Dist: scikit-learn >=1.5.1
Requires-Dist: pyfiglet >=1.0.2
Requires-Dist: pandas >=2.2.2
Requires-Dist: pyarrow >=17.0.0
